iss_tracker/__init__.py
iss_tracker-2.0.0.dist-info/LICENSE
iss_tracker-2.0.0.dist-info/METADATA
iss_tracker-2.0.0.dist-info/WHEEL
iss_tracker-2.0.0.dist-info/entry_points.txt
iss_tracker-2.0.0.dist-info/top_level.txt
iss_tracker-2.0.0.dist-info/RECORD
